letter_writer/__init__.py
letter_writer/app.py
letter_writer/writer.py
writernet/__init__.py
writernet/app.py
writernet/writer.py
writernet-0.2.dist-info/METADATA
writernet-0.2.dist-info/WHEEL
writernet-0.2.dist-info/entry_points.txt
writernet-0.2.dist-info/top_level.txt
writernet-0.2.dist-info/RECORD
