Metadata-Version: 2.1
Name: writernet
Version: 0.2
Summary: A package for automated typing and taking screenshots
Author: Abdulfarith
Author-email: abdullfarith@gmail.com
Classifier: Programming Language :: Python :: 3
Classifier: License :: OSI Approved :: MIT License
Classifier: Operating System :: OS Independent
Requires-Python: >=3.6
Requires-Dist: pyautogui
Requires-Dist: flask
